Tool.py
lutestlib/__init__.py
lutestlib/lulibone.py
lutestlib-1.0.0.dist-info/LICENSE.txt
lutestlib-1.0.0.dist-info/METADATA
lutestlib-1.0.0.dist-info/WHEEL
lutestlib-1.0.0.dist-info/top_level.txt
lutestlib-1.0.0.dist-info/RECORD
