Metadata-Version: 2.1
Name: lutestlib
Version: 1.0.0
Summary: this is lulib
Home-page: https://github.com/
Author: Luleilei
Author-email: 820365542@qq.com
License: UNKNOWN
Platform: UNKNOWN
